piplyr/__init__.py
piplyr/piplyr.py
piplyr-1.4.dist-info/LICENSE
piplyr-1.4.dist-info/METADATA
piplyr-1.4.dist-info/WHEEL
piplyr-1.4.dist-info/top_level.txt
piplyr-1.4.dist-info/RECORD
