Metadata-Version: 2.1
Name: piplyr
Version: 1.4
Summary: dplyr - like data manipulation
Home-page: https://github.com/economer/piplyr
Author: Seyed Pozveh
Author-email: saskosask@gmail.com
Classifier: Programming Language :: Python :: 3
Classifier: License :: OSI Approved :: MIT License
Classifier: Operating System :: OS Independent
Requires-Python: >=3.6
License-File: LICENSE
Requires-Dist: pandas >=1.0.0
Requires-Dist: numpy >=1.18.0
